mkctools/__init__.py
mkctools/basic.py
mkctools/ml_lib.py
mkctools-0.6.4.dist-info/METADATA
mkctools-0.6.4.dist-info/WHEEL
mkctools-0.6.4.dist-info/top_level.txt
mkctools-0.6.4.dist-info/RECORD
